optimization_algorithms_tools/__init__.py
optimization_algorithms_tools/routing.py
optimization_algorithms_tools/structures.py
optimization_algorithms_tools/utilities.py
optimization_algorithms_tools/algorithms/__init__.py
optimization_algorithms_tools/algorithms/_sa.py
optimization_algorithms_tools/algorithms/_ts.py
optimization_algorithms_tools/algorithms/graph_search.py
optimization_algorithms_tools/problems/__init__.py
optimization_algorithms_tools/problems/__problem_base.py
optimization_algorithms_tools/problems/albp.py
optimization_algorithms_tools/problems/sheets.py
optimization_algorithms_tools/problems/sudoku.py
optimization_algorithms_tools/problems/tsp.py
optimization_algorithms_tools-1.0.1.dist-info/LICENSE
optimization_algorithms_tools-1.0.1.dist-info/METADATA
optimization_algorithms_tools-1.0.1.dist-info/WHEEL
optimization_algorithms_tools-1.0.1.dist-info/top_level.txt
optimization_algorithms_tools-1.0.1.dist-info/RECORD
